{
  "main": {
    "id": "52f7e10892a1139f",
    "type": "split",
    "children": [
      {
        "id": "4aa88b3decdac1d8",
        "type": "tabs",
        "children": [
          {
            "id": "66428bc4cc7358fa",
            "type": "leaf",
            "state": {
              "type": "markdown",
              "state": {
                "file": "source/_posts/mini-vue 0 概览.md",
                "mode": "source",
                "backlinks": false,
                "source": false
              }
            }
          },
          {
            "id": "0aa8567b20426d2c",
            "type": "leaf",
            "state": {
              "type": "markdown",
              "state": {
                "file": "template/post.md",
                "mode": "source",
                "backlinks": false,
                "source": false
              }
            }
          },
          {
            "id": "bfd6b2201435e01e",
            "type": "leaf",
            "state": {
              "type": "markdown",
              "state": {
                "file": "source/_posts/mini-vue 0 概览.md",
                "mode": "source",
                "backlinks": false,
                "source": false
              }
            }
          },
          {
            "id": "f10ef8425b6b5151",
            "type": "leaf",
            "state": {
              "type": "markdown",
              "state": {
                "file": "source/_posts/Babel.md",
                "mode": "source",
                "backlinks": false,
                "source": false
              }
            }
          }
        ],
        "currentTab": 3
      }
    ],
    "direction": "vertical"
  },
  "left": {
    "id": "02a2de0a5119d8a3",
    "type": "split",
    "children": [
      {
        "id": "d1d6a5576d3cb765",
        "type": "tabs",
        "children": [
          {
            "id": "d7127129421681c1",
            "type": "leaf",
            "state": {
              "type": "file-explorer",
              "state": {
                "sortOrder": "alphabetical"
              }
            }
          },
          {
            "id": "baf683f7f4c14110",
            "type": "leaf",
            "state": {
              "type": "search",
              "state": {
                "query": "",
                "matchingCase": false,
                "explainSearch": false,
                "collapseAll": false,
                "extraContext": false,
                "sortOrder": "alphabetical"
              }
            }
          },
          {
            "id": "5b5c3014e3120b3f",
            "type": "leaf",
            "state": {
              "type": "starred",
              "state": {}
            }
          }
        ]
      }
    ],
    "direction": "horizontal",
    "width": 300
  },
  "right": {
    "id": "c929140d115f7bf8",
    "type": "split",
    "children": [
      {
        "id": "7a7dba9d3ac74526",
        "type": "tabs",
        "children": [
          {
            "id": "0f607ad1c0bdb937",
            "type": "leaf",
            "state": {
              "type": "backlink",
              "state": {
                "file": "source/_posts/Babel.md",
                "collapseAll": false,
                "extraContext": false,
                "sortOrder": "alphabetical",
                "showSearch": false,
                "searchQuery": "",
                "backlinkCollapsed": false,
                "unlinkedCollapsed": true
              }
            }
          },
          {
            "id": "fea334931609836c",
            "type": "leaf",
            "state": {
              "type": "outgoing-link",
              "state": {
                "file": "source/_posts/Babel.md",
                "linksCollapsed": false,
                "unlinkedCollapsed": true
              }
            }
          },
          {
            "id": "b29386a4edbbfc29",
            "type": "leaf",
            "state": {
              "type": "tag",
              "state": {
                "sortOrder": "frequency",
                "useHierarchy": true
              }
            }
          },
          {
            "id": "9be1833c468e06f9",
            "type": "leaf",
            "state": {
              "type": "outline",
              "state": {
                "file": "source/_posts/Babel.md"
              }
            }
          },
          {
            "id": "4a1dc80886da206f",
            "type": "leaf",
            "state": {
              "type": "review-queue-list-view",
              "state": {}
            }
          },
          {
            "id": "9f5fa0d4df91a918",
            "type": "leaf",
            "state": {
              "type": "reminder-list",
              "state": {}
            }
          }
        ],
        "currentTab": 4
      }
    ],
    "direction": "horizontal",
    "width": 300,
    "collapsed": true
  },
  "active": "f10ef8425b6b5151",
  "lastOpenFiles": [
    "source/_posts/mini-vue 0 概览.md",
    "source/_posts/heLLo.md",
    "source/categories/index.md",
    "source/_posts/两数之和.md",
    "template/post.md",
    "source/images/quicker_2859eb70-7322-44a9-ad00-aa02bcbe2c18.png",
    "source/images/quicker_7afab712-9a9f-45ba-8473-7fb7b55a465e.png",
    "source/_posts/hello-world.md"
  ]
}